[
  {
    "iteration": 0,
    "normal": 0,
    "newUnderlyingPrice": 0,
    "portfolio": {
      "total": 20000,
      "shares": [
        {
          "symbol": "abc",
          "quantity": 100,
          "price": 100,
          "leverage": 1,
          "total": 10000
        },
        {
          "symbol": "abcx",
          "quantity": 1000,
          "price": 10,
          "leverage": 3,
          "total": 10000
        }
      ]
    }
  },
  {
    "iteration": 1,
    "normal": 0.9815347598353193,
    "newUnderlyingPrice": 9.815347598353194,
    "portfolio": {
      "total": 19261.390393412774,
      "shares": [
        {
          "symbol": "abc",
          "quantity": 98.11873802943273,
          "price": 98.15347598353193,
          "leverage": 1,
          "total": 9815.347598353193
        },
        {
          "symbol": "abcx",
          "quantity": 1019.5481224945732,
          "price": 9.446042795059581,
          "leverage": 3,
          "total": 9446.04279505958
        }
      ]
    }
  },
  {
    "iteration": 2,
    "normal": 0.8999834771981959,
    "newUnderlyingPrice": 8.833650661474868,
    "portfolio": {
      "total": 15408.475810458338,
      "shares": [
        {
          "symbol": "abc",
          "quantity": 87.21465451230407,
          "price": 88.33650661474869,
          "leverage": 1,
          "total": 8667.466550967778
        },
        {
          "symbol": "abcx",
          "quantity": 1165.2322358805868,
          "price": 6.6117617312629005,
          "leverage": 3,
          "total": 6741.009259490559
        }
      ]
    }
  },
  {
    "iteration": 3,
    "normal": 0.9060718178199568,
    "newUnderlyingPrice": 8.003921912828998,
    "portfolio": {
      "total": 12513.8955643753,
      "shares": [
        {
          "symbol": "abc",
          "quantity": 78.17352355922876,
          "price": 80.03921912828999,
          "leverage": 1,
          "total": 6980.59284370841
        },
        {
          "symbol": "abcx",
          "quantity": 1317.621251191528,
          "price": 4.748669449987602,
          "leverage": 3,
          "total": 5533.30272066689
        }
      ]
    }
  },
  {
    "iteration": 4,
    "normal": 0.9236562540113514,
    "newUnderlyingPrice": 7.392872531403003,
    "portfolio": {
      "total": 10603.180235785012,
      "shares": [
        {
          "symbol": "abc",
          "quantity": 71.71218082514919,
          "price": 73.92872531403003,
          "leverage": 1,
          "total": 5779.268950040078
        },
        {
          "symbol": "abcx",
          "quantity": 1448.096241961346,
          "price": 3.6610758071658753,
          "leverage": 3,
          "total": 4823.911285744934
        }
      ]
    }
  },
  {
    "iteration": 5,
    "normal": 1.1754084535627587,
    "newUnderlyingPrice": 8.689644869523,
    "portfolio": {
      "total": 14322.955131797524,
      "shares": [
        {
          "symbol": "abc",
          "quantity": 82.4139268454578,
          "price": 86.89644869523,
          "leverage": 1,
          "total": 6231.5338418956335
        },
        {
          "symbol": "abcx",
          "quantity": 1281.6671359098434,
          "price": 5.587626744298859,
          "leverage": 3,
          "total": 8091.421289901889
        }
      ]
    }
  },
  {
    "iteration": 6,
    "normal": 0.9196096889830437,
    "newUnderlyingPrice": 7.9910816158351485,
    "portfolio": {
      "total": 12020.101496343297,
      "shares": [
        {
          "symbol": "abc",
          "quantity": 75.2094777290488,
          "price": 79.91081615835148,
          "leverage": 1,
          "total": 6585.764157035205
        },
        {
          "symbol": "abcx",
          "quantity": 1417.4468841609876,
          "price": 4.240053588836315,
          "leverage": 3,
          "total": 5434.337339308093
        }
      ]
    }
  },
  {
    "iteration": 7,
    "normal": 1.1131573791984712,
    "newUnderlyingPrice": 8.89533146844414,
    "portfolio": {
      "total": 14740.427862394958,
      "shares": [
        {
          "symbol": "abc",
          "quantity": 82.85485433952678,
          "price": 88.95331468444138,
          "leverage": 1,
          "total": 6690.132339684564
        },
        {
          "symbol": "abcx",
          "quantity": 1297.7022697992193,
          "price": 5.679433644157685,
          "leverage": 3,
          "total": 8050.295522710394
        }
      ]
    }
  },
  {
    "iteration": 8,
    "normal": 0.9337323834790796,
    "newUnderlyingPrice": 8.305859053866808,
    "portfolio": {
      "total": 12786.801820515999,
      "shares": [
        {
          "symbol": "abc",
          "quantity": 76.97458948910939,
          "price": 83.05859053866806,
          "leverage": 1,
          "total": 6881.807420727739
        },
        {
          "symbol": "abcx",
          "quantity": 1405.0361966940566,
          "price": 4.55034605179652,
          "leverage": 3,
          "total": 5904.99439978826
        }
      ]
    }
  },
  {
    "iteration": 9,
    "normal": 1.119776626778747,
    "newUnderlyingPrice": 9.300706833838689,
    "portfolio": {
      "total": 15849.921799215494,
      "shares": [
        {
          "symbol": "abc",
          "quantity": 85.2081571991327,
          "price": 93.00706833838687,
          "leverage": 1,
          "total": 7159.180904932873
        },
        {
          "symbol": "abcx",
          "quantity": 1281.232182248037,
          "price": 6.18542135407705,
          "leverage": 3,
          "total": 8690.74089428262
        }
      ]
    }
  },
  {
    "iteration": 10,
    "normal": 0.9415043921595024,
    "newUnderlyingPrice": 8.756656334247024,
    "portfolio": {
      "total": 13995.620179476566,
      "shares": [
        {
          "symbol": "abc",
          "quantity": 79.91417982649445,
          "price": 87.56656334247023,
          "leverage": 1,
          "total": 7461.385494673014
        },
        {
          "symbol": "abcx",
          "quantity": 1372.1300082906746,
          "price": 5.099961408508059,
          "leverage": 3,
          "total": 6534.234684803552
        }
      ]
    }
  }
]